morfeus/__init__.py
morfeus/__main__.py
morfeus/bite_angle.py
morfeus/buried_volume.py
morfeus/calculators.py
morfeus/cone_angle.py
morfeus/config.py
morfeus/conformer.py
morfeus/d3_data.py
morfeus/data.py
morfeus/dispersion.py
morfeus/geometry.py
morfeus/io.py
morfeus/local_force.py
morfeus/plotting.py
morfeus/py.typed
morfeus/pyramidalization.py
morfeus/qc.py
morfeus/sasa.py
morfeus/solid_angle.py
morfeus/sterimol.py
morfeus/typing.py
morfeus/utils.py
morfeus/visible_volume.py
morfeus/xtb.py
morfeus_ml-0.8.0.dist-info/licenses/LICENSE
morfeus_ml-0.8.0.dist-info/METADATA
morfeus_ml-0.8.0.dist-info/WHEEL
morfeus_ml-0.8.0.dist-info/entry_points.txt
morfeus_ml-0.8.0.dist-info/top_level.txt
morfeus_ml-0.8.0.dist-info/RECORD
