Metadata-Version: 2.4
Name: morfeus-ml
Version: 0.8.0
Summary: A Python package for calculating molecular features
Home-page: https://github.com/digital-chemistry-laboratory/morfeus
Author: Kjell Jorner
Author-email: kjell.jorner@gmail.com
License: MIT
Classifier: Programming Language :: Python :: 3
Classifier: License :: OSI Approved :: MIT License
Classifier: Operating System :: OS Independent
Requires-Python: >=3.10
License-File: LICENSE
Requires-Dist: fire
Requires-Dist: numpy
Requires-Dist: packaging
Requires-Dist: scipy
Dynamic: author
Dynamic: author-email
Dynamic: classifier
Dynamic: description
Dynamic: description-content-type
Dynamic: home-page
Dynamic: license
Dynamic: license-file
Dynamic: requires-dist
Dynamic: requires-python
Dynamic: summary
